setup.py
src/colors.py
src/weather.py
terminal_weather.egg-info/PKG-INFO
terminal_weather.egg-info/SOURCES.txt
terminal_weather.egg-info/dependency_links.txt
terminal_weather.egg-info/top_level.txt