Metadata-Version: 1.0
Name: terminal-weather
Version: 0.1
Summary: terminal weather script
Home-page: UNKNOWN
Author: UNKNOWN
Author-email: UNKNOWN
License: UNKNOWN
Platform: UNKNOWN
